citybrain_platform/__init__.py
citybrain_platform/computing/__init__.py
citybrain_platform/computing/api.py
citybrain_platform/computing/client.py
citybrain_platform/computing/data_types.py
citybrain_platform/data/__init__.py
citybrain_platform/data/api.py
citybrain_platform/data/client.py
citybrain_platform/storage/__init__.py
citybrain_platform/storage/api.py
citybrain_platform/storage/client.py
citybrain_platform/storage/data_types.py
citybrain_platform-0.4.3.dist-info/LICENSE
citybrain_platform-0.4.3.dist-info/METADATA
citybrain_platform-0.4.3.dist-info/WHEEL
citybrain_platform-0.4.3.dist-info/top_level.txt
citybrain_platform-0.4.3.dist-info/RECORD
